strapi_api_client/__init__.py
strapi_api_client/api_client.py
strapi_api_client/errors.py
strapi_api_client/requestor.py
strapi_api_client/utils.py
strapi_api_client/version.py
strapi_api_client/resources/__init__.py
strapi_api_client/resources/base.py
strapi_api_client/resources/community.py
strapi_api_client/resources/group.py
strapi_api_client/resources/subgroup.py
strapi_api_client-0.4.0.dist-info/LICENSE
strapi_api_client-0.4.0.dist-info/METADATA
strapi_api_client-0.4.0.dist-info/WHEEL
strapi_api_client-0.4.0.dist-info/top_level.txt
strapi_api_client-0.4.0.dist-info/RECORD
