Metadata-Version: 2.1
Name: strapi-api-client
Version: 0.4.0
Summary: Strapi API Client is used for maintaining a communication with the Strapi CMS by HTTP transfer protocol.
Home-page: https://github.com/culturepulse/strapi-api-client
Author: Adam Žúrek
Author-email: adam@culturepulse.ai
License: MIT
Classifier: Development Status :: 4 - Beta
Classifier: Environment :: Console
Classifier: Programming Language :: Python
Classifier: Programming Language :: Python :: 3.9
Classifier: Programming Language :: Python :: 3.10
Classifier: Programming Language :: Python :: Implementation :: PyPy
Classifier: Intended Audience :: Developers
Classifier: License :: OSI Approved :: MIT License
Classifier: Topic :: Software Development
Classifier: Topic :: Internet :: WWW/HTTP
Classifier: Topic :: System :: Networking
Classifier: Topic :: Communications
Classifier: Topic :: Software Development :: Libraries :: Python Modules
License-File: LICENSE
